{
  "cinematicMode": true,
  "arenas": {
    "dublin": {
      "type": "city",
      "displayName": "Dublin",
      "presets": {
        "parallax": "city",
        "lighting": "foggy_night",
        "weather": "london_fog",
        "animation": "city"
      },
      "victoryMusic": "soundtrack_walking_on_cars"
    },
    "galway": {
      "type": "mountain",
      "displayName": "Galway",
      "presets": {
        "parallax": "mountain",
        "lighting": "outdoor_day",
        "weather": "tokyo_rain",
        "animation": "mountain"
      },
      "victoryMusic": "soundtrack_apocalypse"
    },
    "london": {
      "type": "city",
      "displayName": "London",
      "presets": {
        "parallax": "city",
        "lighting": "foggy_night",
        "weather": "london_fog",
        "animation": "city"
      },
      "victoryMusic": "soundtrack_apocalypse"
    },
    "paris": {
      "type": "city",
      "displayName": "Paris",
      "presets": {
        "parallax": "city",
        "lighting": "outdoor_day",
        "weather": null,
        "animation": "city"
      },
      "victoryMusic": "soundtrack_walking_on_cars"
    },
    "switzerland": {
      "type": "mountain",
      "displayName": "Switzerland",
      "presets": {
        "parallax": "mountain",
        "lighting": "outdoor_day",
        "weather": "mountain_snow",
        "animation": "mountain"
      },
      "victoryMusic": "soundtrack_walking_on_cars"
    },
    "austria": {
      "type": "city",
      "displayName": "Austria",
      "presets": {
        "parallax": "city",
        "lighting": "outdoor_day",
        "weather": null,
        "animation": "city"
      },
      "victoryMusic": "soundtrack_walking_on_cars"
    },
    "germany": {
      "type": "city",
      "displayName": "Germany",
      "presets": {
        "parallax": "city",
        "lighting": "outdoor_day",
        "weather": null,
        "animation": "city"
      },
      "victoryMusic": "soundtrack_walking_on_cars"
    },
    "budapest": {
      "type": "city",
      "displayName": "Budapest",
      "presets": {
        "parallax": "city",
        "lighting": "outdoor_day",
        "weather": null,
        "animation": "city"
      },
      "victoryMusic": "soundtrack_walking_on_cars"
    },
    "istambul": {
      "type": "city",
      "displayName": "Istanbul",
      "presets": {
        "parallax": "city",
        "lighting": "outdoor_night",
        "weather": "desert_wind",
        "animation": "city"
      },
      "victoryMusic": "soundtrack_walking_on_cars"
    },

    "avignon": {
      "type": "city",
      "displayName": "Avignon",
      "presets": {
        "parallax": "city",
        "lighting": "outdoor_day",
        "weather": null,
        "animation": "city"
      },
      "victoryMusic": "soundtrack_walking_on_cars"
    },
    "amsterdam": {
      "type": "city",
      "displayName": "Amsterdam",
      "presets": {
        "parallax": "city",
        "lighting": "outdoor_day",
        "weather": null,
        "animation": "city"
      },
      "victoryMusic": "soundtrack_walking_on_cars"
    },
    "malta": {
      "type": "city",
      "displayName": "Malta",
      "presets": {
        "parallax": "city",
        "lighting": "outdoor_day",
        "weather": null,
        "animation": "city"
      },
      "victoryMusic": "soundtrack_walking_on_cars"
    },
    "bolivia": {
      "type": "mountain",
      "displayName": "Bolivia",
      "presets": {
        "parallax": "mountain",
        "lighting": "outdoor_day",
        "weather": null,
        "animation": "mountain"
      },
      "victoryMusic": "soundtrack_apocalypse"
    },
    "sanfrancisco": {
      "type": "city",
      "displayName": "San Francisco",
      "presets": {
        "parallax": "city",
        "lighting": "outdoor_day",
        "weather": "london_fog",
        "animation": "city"
      },
      "victoryMusic": "soundtrack_walking_on_cars"
    },
    "taipei": {
      "type": "city",
      "displayName": "Taipei",
      "presets": {
        "parallax": "city",
        "lighting": "outdoor_night",
        "weather": "tokyo_rain",
        "animation": "city"
      },
      "victoryMusic": "soundtrack_apocalypse"
    },
    "canada": {
      "type": "mountain",
      "displayName": "Canada",
      "presets": {
        "parallax": "mountain",
        "lighting": "outdoor_day",
        "weather": "mountain_snow",
        "animation": "mountain"
      },
      "victoryMusic": "soundtrack_walking_on_cars"
    }
  },
  "combat": {
    "global": {
      "walkSpeed": 160,
      "jumpPower": -600,
      "attackDamage": 10,
      "maxHealth": 100
    },
    "damage": {
      "LIGHT_ATTACK": 10,
      "HEAVY_ATTACK": 20
    },
    "match": {
      "ROUNDS": 3,
      "TIME": 99,
      "LOW_TIME_THRESHOLD": 10
    },
    "combo": {
      "thresholds": {
        "SMALL": 3,
        "MEDIUM": 5,
        "LARGE": 7
      },
      "voiceLines": {
        "3": "combo_3",
        "5": "combo_5"
      }
    },
    "attackRange": 80
  },
  "difficulty": {
    "easy": {
      "aggression": 0.2,
      "blockRate": 0.1,
      "reactionTime": {
        "min": 800,
        "max": 1200
      },
      "mistakeChance": 0.4
    },
    "medium": {
      "aggression": 0.5,
      "blockRate": 0.4,
      "reactionTime": {
        "min": 400,
        "max": 700
      },
      "mistakeChance": 0.2
    },
    "hard": {
      "aggression": 0.9,
      "blockRate": 0.8,
      "reactionTime": {
        "min": 150,
        "max": 250
      },
      "mistakeChance": 0.05
    },
    "nightmare": {
      "aggression": 1.0,
      "blockRate": 1.0,
      "reactionTime": {
        "min": 0,
        "max": 50
      },
      "mistakeChance": 0.0
    }
  },
  "roster": [
    {
      "id": "ann",
      "displayName": "Ann",
      "portraitPath": "/assets/fighters/ann/portrait.png",
      "iconPath": "/assets/fighters/ann/portrait.png",
      "fullBodyPath": "/assets/fighters/ann/fullBody.png",
      "victoryPath": "/assets/fighters/ann/victory.png",
      "personality": "aggressive"
    },
    {
      "id": "mom",
      "displayName": "媽媽",
      "portraitPath": "/assets/fighters/mom/portrait.png",
      "iconPath": "/assets/fighters/mom/portrait.png",
      "fullBodyPath": "/assets/fighters/mom/fullBody.png",
      "victoryPath": "/assets/fighters/mom/victory.png",
      "personality": "aggressive"
    },
    {
      "id": "dad",
      "displayName": "爸爸",
      "portraitPath": "/assets/fighters/dad/portrait.png",
      "iconPath": "/assets/fighters/dad/portrait.png",
      "fullBodyPath": "/assets/fighters/dad/fullBody.png",
      "victoryPath": "/assets/fighters/dad/victory.png",
      "personality": "aggressive"
    },
    {
      "id": "brother",
      "displayName": "柚子",
      "portraitPath": "/assets/fighters/brother/portrait.png",
      "iconPath": "/assets/fighters/brother/portrait.png",
      "fullBodyPath": "/assets/fighters/brother/fullBody.png",
      "victoryPath": "/assets/fighters/brother/victory.png",
      "personality": "aggressive"
    },
    {
      "id": "fat",
      "displayName": "Fat",
      "portraitPath": "/assets/fighters/fat/portrait.png",
      "iconPath": "/assets/fighters/fat/portrait.png",
      "fullBodyPath": "/assets/fighters/fat/fullBody.png",
      "victoryPath": "/assets/fighters/fat/victory.png",
      "personality": "aggressive"
    },
    {
      "id": "fresway_worker",
      "displayName": "Freshway Worker",
      "portraitPath": "/assets/fighters/fresway_worker/portrait.png",
      "iconPath": "/assets/fighters/fresway_worker/portrait.png",
      "fullBodyPath": "/assets/fighters/fresway_worker/fullBody.png",
      "victoryPath": "/assets/fighters/fresway_worker/victory.png",
      "personality": "aggressive"
    }
  ]
}
